otakudesu/__init__.py
otakudesu/__main__.py
otakudesu/otaku.py
otakudesu/utils.py
otakudesu-0.0.9.dist-info/METADATA
otakudesu-0.0.9.dist-info/WHEEL
otakudesu-0.0.9.dist-info/top_level.txt
otakudesu-0.0.9.dist-info/RECORD
